[{"gen":1,"name":"mist","introduced":1,"formatted_name":"Mist","field_state_class":"other","damage_percent":0,"max_layers":1,"only_grounded":false,"stat_modifications":{},"target":"all_allies","effects":{"prevents_stat_drop":true},"causes_status":{},"prevents_status":{},"boosts_type":{},"resists_type":{},"activates_ability":{},"activates_item":{},"enhances_move":{},"hinders_move":{},"description":"Protects the user from having its stats decreased by the opponent's status moves."},{"gen":2,"name":"mist","introduced":1,"formatted_name":"Mist","field_state_class":"other","damage_percent":0,"max_layers":1,"only_grounded":false,"stat_modifications":{},"target":"all_allies","effects":{"prevents_stat_drop":true},"causes_status":{},"prevents_status":{},"boosts_type":{},"resists_type":{},"activates_ability":{},"activates_item":{},"enhances_move":{},"hinders_move":{},"description":"Protects the user from having its stats decreased by the opponent."},{"gen":3,"name":"mist","introduced":1,"formatted_name":"Mist","field_state_class":"other","damage_percent":0,"max_layers":1,"only_grounded":false,"stat_modifications":{},"target":"all_allies","effects":{"prevents_stat_drop":true},"causes_status":{},"prevents_status":{},"boosts_type":{},"resists_type":{},"activates_ability":{},"activates_item":{},"enhances_move":{},"hinders_move":{},"description":"Protects the user and its allies from having its stats decreased by the opponent."},{"gen":4,"name":"mist","introduced":1,"formatted_name":"Mist","field_state_class":"other","damage_percent":0,"max_layers":1,"only_grounded":false,"stat_modifications":{},"target":"all_allies","effects":{"prevents_stat_drop":true},"causes_status":{},"prevents_status":{},"boosts_type":{},"resists_type":{},"activates_ability":{},"activates_item":{},"enhances_move":{},"hinders_move":{},"description":"Protects the user and its allies from having its stats decreased by the opponent."},{"gen":5,"name":"mist","introduced":1,"formatted_name":"Mist","field_state_class":"other","damage_percent":0,"max_layers":1,"only_grounded":false,"stat_modifications":{},"target":"all_allies","effects":{"prevents_stat_drop":true},"causes_status":{},"prevents_status":{},"boosts_type":{},"resists_type":{},"activates_ability":{},"activates_item":{},"enhances_move":{},"hinders_move":{},"description":"Protects the user and its allies from having its stats decreased by the opponent."},{"gen":6,"name":"mist","introduced":1,"formatted_name":"Mist","field_state_class":"other","damage_percent":0,"max_layers":1,"only_grounded":false,"stat_modifications":{},"target":"all_allies","effects":{"prevents_stat_drop":true},"causes_status":{},"prevents_status":{},"boosts_type":{},"resists_type":{},"activates_ability":{},"activates_item":{},"enhances_move":{},"hinders_move":{},"description":"Protects the user and its allies from having its stats decreased by the opponent."},{"gen":7,"name":"mist","introduced":1,"formatted_name":"Mist","field_state_class":"other","damage_percent":0,"max_layers":1,"only_grounded":false,"stat_modifications":{},"target":"all_allies","effects":{"prevents_stat_drop":true},"causes_status":{},"prevents_status":{},"boosts_type":{},"resists_type":{},"activates_ability":{},"activates_item":{},"enhances_move":{},"hinders_move":{},"description":"Protects the user and its allies from having its stats decreased by the opponent."},{"gen":8,"name":"mist","introduced":1,"formatted_name":"Mist","field_state_class":"other","damage_percent":0,"max_layers":1,"only_grounded":false,"stat_modifications":{},"target":"all_allies","effects":{"prevents_stat_drop":true},"causes_status":{},"prevents_status":{},"boosts_type":{},"resists_type":{},"activates_ability":{},"activates_item":{},"enhances_move":{},"hinders_move":{},"description":"Protects the user and its allies from having its stats decreased by the opponent."},{"gen":2,"name":"safeguard","introduced":2,"formatted_name":"Safeguard","field_state_class":"other","damage_percent":0,"max_layers":1,"only_grounded":false,"stat_modifications":{},"target":"all_allies","effects":{},"causes_status":{},"prevents_status":{"burn":true,"freeze":true,"paralysis":true,"poison":true,"bad_poison":true,"sleep":true,"confusion":true},"boosts_type":{},"resists_type":{},"activates_ability":{},"activates_item":{},"enhances_move":{},"hinders_move":{},"description":"Protects against non-volatile status conditions and confusion in most cases."},{"gen":3,"name":"safeguard","introduced":2,"formatted_name":"Safeguard","field_state_class":"other","damage_percent":0,"max_layers":1,"only_grounded":false,"stat_modifications":{},"target":"all_allies","effects":{},"causes_status":{},"prevents_status":{"burn":true,"freeze":true,"paralysis":true,"poison":true,"bad_poison":true,"sleep":true,"confusion":true,"drowsy":true},"boosts_type":{},"resists_type":{},"activates_ability":{},"activates_item":{},"enhances_move":{},"hinders_move":{},"description":"Protects against non-volatile status conditions and confusion in most cases."},{"gen":4,"name":"safeguard","introduced":2,"formatted_name":"Safeguard","field_state_class":"other","damage_percent":0,"max_layers":1,"only_grounded":false,"stat_modifications":{},"target":"all_allies","effects":{},"causes_status":{},"prevents_status":{"burn":true,"freeze":true,"paralysis":true,"poison":true,"bad_poison":true,"sleep":true,"confusion":true,"drowsy":true},"boosts_type":{},"resists_type":{},"activates_ability":{},"activates_item":{},"enhances_move":{},"hinders_move":{},"description":"Protects against non-volatile status conditions and confusion in most cases."},{"gen":5,"name":"safeguard","introduced":2,"formatted_name":"Safeguard","field_state_class":"other","damage_percent":0,"max_layers":1,"only_grounded":false,"stat_modifications":{},"target":"all_allies","effects":{},"causes_status":{},"prevents_status":{"burn":true,"freeze":true,"paralysis":true,"poison":true,"bad_poison":true,"sleep":true,"confusion":true,"drowsy":true},"boosts_type":{},"resists_type":{},"activates_ability":{},"activates_item":{},"enhances_move":{},"hinders_move":{},"description":"Protects against non-volatile status conditions and confusion in most cases."},{"gen":6,"name":"safeguard","introduced":2,"formatted_name":"Safeguard","field_state_class":"other","damage_percent":0,"max_layers":1,"only_grounded":false,"stat_modifications":{},"target":"all_allies","effects":{},"causes_status":{},"prevents_status":{"burn":true,"freeze":true,"paralysis":true,"poison":true,"bad_poison":true,"sleep":true,"confusion":true,"drowsy":true},"boosts_type":{},"resists_type":{},"activates_ability":{},"activates_item":{},"enhances_move":{},"hinders_move":{},"description":"Protects against non-volatile status conditions and confusion in most cases."},{"gen":7,"name":"safeguard","introduced":2,"formatted_name":"Safeguard","field_state_class":"other","damage_percent":0,"max_layers":1,"only_grounded":false,"stat_modifications":{},"target":"all_allies","effects":{},"causes_status":{},"prevents_status":{"burn":true,"freeze":true,"paralysis":true,"poison":true,"bad_poison":true,"sleep":true,"confusion":true,"drowsy":true},"boosts_type":{},"resists_type":{},"activates_ability":{},"activates_item":{},"enhances_move":{},"hinders_move":{},"description":"Protects against non-volatile status conditions and confusion in most cases."},{"gen":8,"name":"safeguard","introduced":2,"formatted_name":"Safeguard","field_state_class":"other","damage_percent":0,"max_layers":1,"only_grounded":false,"stat_modifications":{},"target":"all_allies","effects":{},"causes_status":{},"prevents_status":{"burn":true,"freeze":true,"paralysis":true,"poison":true,"bad_poison":true,"sleep":true,"confusion":true,"drowsy":true},"boosts_type":{},"resists_type":{},"activates_ability":{},"activates_item":{},"enhances_move":{},"hinders_move":{},"description":"Protects against non-volatile status conditions and confusion in most cases."},{"gen":4,"name":"tailwind","introduced":4,"formatted_name":"Tailwind","field_state_class":"other","damage_percent":0,"max_layers":1,"only_grounded":false,"stat_modifications":{"speed":[2,"all_allies",100]},"target":"all_allies","effects":{},"causes_status":{},"prevents_status":{},"boosts_type":{},"resists_type":{},"activates_ability":{},"activates_item":{},"enhances_move":{},"hinders_move":{},"description":"Doubles the speed stat of the user and its allies."},{"gen":5,"name":"tailwind","introduced":4,"formatted_name":"Tailwind","field_state_class":"other","damage_percent":0,"max_layers":1,"only_grounded":false,"stat_modifications":{"speed":[2,"all_allies",100]},"target":"all_allies","effects":{},"causes_status":{},"prevents_status":{},"boosts_type":{},"resists_type":{},"activates_ability":{},"activates_item":{},"enhances_move":{},"hinders_move":{},"description":"Doubles the speed stat of the user and its allies."},{"gen":6,"name":"tailwind","introduced":4,"formatted_name":"Tailwind","field_state_class":"other","damage_percent":0,"max_layers":1,"only_grounded":false,"stat_modifications":{"speed":[2,"all_allies",100]},"target":"all_allies","effects":{},"causes_status":{},"prevents_status":{},"boosts_type":{},"resists_type":{},"activates_ability":{},"activates_item":{},"enhances_move":{},"hinders_move":{},"description":"Doubles the speed stat of the user and its allies."},{"gen":7,"name":"tailwind","introduced":4,"formatted_name":"Tailwind","field_state_class":"other","damage_percent":0,"max_layers":1,"only_grounded":false,"stat_modifications":{"speed":[2,"all_allies",100]},"target":"all_allies","effects":{},"causes_status":{},"prevents_status":{},"boosts_type":{},"resists_type":{},"activates_ability":{},"activates_item":{},"enhances_move":{},"hinders_move":{},"description":"Doubles the speed stat of the user and its allies."},{"gen":8,"name":"tailwind","introduced":4,"formatted_name":"Tailwind","field_state_class":"other","damage_percent":0,"max_layers":1,"only_grounded":false,"stat_modifications":{"speed":[2,"all_allies",100]},"target":"all_allies","effects":{},"causes_status":{},"prevents_status":{},"boosts_type":{},"resists_type":{},"activates_ability":{},"activates_item":{},"enhances_move":{},"hinders_move":{},"description":"Doubles the speed stat of the user and its allies."},{"gen":8,"name":"vine_lash","introduced":8,"formatted_name":"Vine lash","field_state_class":"other","damage_percent":16.67,"max_layers":1,"only_grounded":false,"stat_modifications":{},"target":"all_foes","effects":{},"causes_status":{},"prevents_status":{},"boosts_type":{},"resists_type":{},"activates_ability":{},"activates_item":{},"enhances_move":{},"hinders_move":{},"description":"Inflicts Grass-type damage equal to 1/6 of the opponents max HP each turn."},{"gen":8,"name":"wildfire","introduced":8,"formatted_name":"Wildfire","field_state_class":"other","damage_percent":16.67,"max_layers":1,"only_grounded":false,"stat_modifications":{},"target":"all_foes","effects":{},"causes_status":{},"prevents_status":{},"boosts_type":{},"resists_type":{},"activates_ability":{},"activates_item":{},"enhances_move":{},"hinders_move":{},"description":"Inflicts Fire-type damage equal to 1/6 of the opponents max HP each turn."},{"gen":8,"name":"cannonade","introduced":8,"formatted_name":"Cannonade","field_state_class":"other","damage_percent":16.67,"max_layers":1,"only_grounded":false,"stat_modifications":{},"target":"all_foes","effects":{},"causes_status":{},"prevents_status":{},"boosts_type":{},"resists_type":{},"activates_ability":{},"activates_item":{},"enhances_move":{},"hinders_move":{},"description":"Inflicts Water-type damage equal to 1/6 of the opponents max HP each turn."},{"gen":8,"name":"volcalith","introduced":8,"formatted_name":"Volcalith","field_state_class":"other","damage_percent":16.67,"max_layers":1,"only_grounded":false,"stat_modifications":{},"target":"all_foes","effects":{},"causes_status":{},"prevents_status":{},"boosts_type":{},"resists_type":{},"activates_ability":{},"activates_item":{},"enhances_move":{},"hinders_move":{},"description":"Inflicts Rock-type damage equal to 1/6 of the opponents max HP each turn."},{"gen":4,"name":"gravity","introduced":4,"formatted_name":"Gravity","field_state_class":"other","damage_percent":0,"max_layers":1,"only_grounded":false,"stat_modifications":{"accuracy":[1.67,"all",100]},"effects":{"grounds":true},"causes_status":{},"prevents_status":{},"boosts_type":{},"resists_type":{},"activates_ability":{},"activates_item":{},"enhances_move":{},"hinders_move":{"bounce":true,"fly":true,"high_jump_kick":true,"jump_kick":true,"magnet_rise":true,"splash":true},"description":"Grounds all Pokemon on the field and causes moves to have increased accuracy."},{"gen":5,"name":"gravity","introduced":4,"formatted_name":"Gravity","field_state_class":"other","damage_percent":0,"max_layers":1,"only_grounded":false,"stat_modifications":{"accuracy":[1.67,"all",100]},"effects":{"grounds":true},"causes_status":{},"prevents_status":{},"boosts_type":{},"resists_type":{},"activates_ability":{},"activates_item":{},"enhances_move":{},"hinders_move":{"bounce":true,"fly":true,"high_jump_kick":true,"jump_kick":true,"magnet_rise":true,"sky_drop":true,"splash":true,"telekinesis":true},"description":"Grounds all Pokemon on the field and causes moves to have increased accuracy."},{"gen":6,"name":"gravity","introduced":4,"formatted_name":"Gravity","field_state_class":"other","damage_percent":0,"max_layers":1,"only_grounded":false,"stat_modifications":{"accuracy":[1.67,"all",100]},"effects":{"grounds":true},"causes_status":{},"prevents_status":{},"boosts_type":{},"resists_type":{},"activates_ability":{},"activates_item":{},"enhances_move":{},"hinders_move":{"bounce":true,"fly":true,"flying_press":true,"high_jump_kick":true,"jump_kick":true,"magnet_rise":true,"sky_drop":true,"splash":true,"telekinesis":true},"description":"Grounds all Pokemon on the field and causes moves to have increased accuracy."},{"gen":7,"name":"gravity","introduced":4,"formatted_name":"Gravity","field_state_class":"other","damage_percent":0,"max_layers":1,"only_grounded":false,"stat_modifications":{"accuracy":[1.67,"all",100]},"effects":{"grounds":true},"causes_status":{},"prevents_status":{},"boosts_type":{},"resists_type":{},"activates_ability":{},"activates_item":{},"enhances_move":{},"hinders_move":{"bounce":true,"fly":true,"flying_press":true,"high_jump_kick":true,"jump_kick":true,"magnet_rise":true,"sky_drop":true,"splash":true,"telekinesis":true},"description":"Grounds all Pokemon on the field and causes moves to have increased accuracy."},{"gen":8,"name":"gravity","introduced":4,"formatted_name":"Gravity","field_state_class":"other","damage_percent":0,"max_layers":1,"only_grounded":false,"stat_modifications":{"accuracy":[1.67,"all",100]},"target":"all_foes","effects":{"grounds":true},"causes_status":{},"prevents_status":{},"boosts_type":{},"resists_type":{},"activates_ability":{},"activates_item":{},"enhances_move":{"grav_apple":true},"hinders_move":{"bounce":true,"fly":true,"flying_press":true,"high_jump_kick":true,"jump_kick":true,"magnet_rise":true,"sky_drop":true,"splash":true,"telekinesis":true},"description":"Grounds all Pokemon on the field and causes moves to have increased accuracy."},{"gen":1,"name":"reflect","introduced":1,"formatted_name":"Reflect","field_state_class":"screen","damage_percent":0,"max_layers":1,"only_grounded":false,"stat_modifications":{"defense":[2,"all_allies",100]},"target":"all_allies","effects":{},"causes_status":{},"prevents_status":{},"boosts_type":{},"resists_type":{},"activates_ability":{},"activates_item":{},"enhances_move":{},"hinders_move":{},"description":"Doubles defense."},{"gen":2,"name":"reflect","introduced":1,"formatted_name":"Reflect","field_state_class":"screen","damage_percent":0,"max_layers":1,"only_grounded":false,"stat_modifications":{"defense":[2,"all_allies",100]},"target":"all_allies","effects":{},"causes_status":{},"prevents_status":{},"boosts_type":{},"resists_type":{},"activates_ability":{},"activates_item":{},"enhances_move":{},"hinders_move":{},"description":"Doubles defense."},{"gen":3,"name":"reflect","introduced":1,"formatted_name":"Reflect","field_state_class":"screen","damage_percent":0,"max_layers":1,"only_grounded":false,"stat_modifications":{"defense":[1,"all_allies",100]},"target":"all_allies","effects":{},"causes_status":{},"prevents_status":{},"boosts_type":{},"resists_type":{},"activates_ability":{},"activates_item":{},"enhances_move":{},"hinders_move":{},"description":"Cuts the physical damage received in half (but does not increase defense)."},{"gen":4,"name":"reflect","introduced":1,"formatted_name":"Reflect","field_state_class":"screen","damage_percent":0,"max_layers":1,"only_grounded":false,"stat_modifications":{"defense":[1,"all_allies",100]},"target":"all_allies","effects":{},"causes_status":{},"prevents_status":{},"boosts_type":{},"resists_type":{},"activates_ability":{},"activates_item":{},"enhances_move":{},"hinders_move":{},"description":"Cuts the physical damage received in half (but does not increase defense)."},{"gen":5,"name":"reflect","introduced":1,"formatted_name":"Reflect","field_state_class":"screen","damage_percent":0,"max_layers":1,"only_grounded":false,"stat_modifications":{"defense":[1,"all_allies",100]},"target":"all_allies","effects":{},"causes_status":{},"prevents_status":{},"boosts_type":{},"resists_type":{},"activates_ability":{},"activates_item":{},"enhances_move":{},"hinders_move":{},"description":"Cuts the physical damage received in half (but does not increase defense)."},{"gen":6,"name":"reflect","introduced":1,"formatted_name":"Reflect","field_state_class":"screen","damage_percent":0,"max_layers":1,"only_grounded":false,"stat_modifications":{"defense":[1,"all_allies",100]},"target":"all_allies","effects":{},"causes_status":{},"prevents_status":{},"boosts_type":{},"resists_type":{},"activates_ability":{},"activates_item":{},"enhances_move":{},"hinders_move":{},"description":"Cuts the physical damage received in half (but does not increase defense)."},{"gen":7,"name":"reflect","introduced":1,"formatted_name":"Reflect","field_state_class":"screen","damage_percent":0,"max_layers":1,"only_grounded":false,"stat_modifications":{"defense":[1,"all_allies",100]},"target":"all_allies","effects":{},"causes_status":{},"prevents_status":{},"boosts_type":{},"resists_type":{},"activates_ability":{},"activates_item":{},"enhances_move":{},"hinders_move":{},"description":"Cuts the physical damage received in half (but does not increase defense)."},{"gen":8,"name":"reflect","introduced":1,"formatted_name":"Reflect","field_state_class":"screen","damage_percent":0,"max_layers":1,"only_grounded":false,"stat_modifications":{"defense":[1,"all_allies",100]},"target":"all_allies","effects":{},"causes_status":{},"prevents_status":{},"boosts_type":{},"resists_type":{},"activates_ability":{},"activates_item":{},"enhances_move":{},"hinders_move":{},"description":"Cuts the physical damage received in half (but does not increase defense)."},{"gen":1,"name":"light_screen","introduced":1,"formatted_name":"Light screen","field_state_class":"screen","damage_percent":0,"max_layers":1,"only_grounded":false,"stat_modifications":{"special_defense":[2,"all_allies",100]},"target":"all_allies","effects":{},"causes_status":{},"prevents_status":{},"boosts_type":{},"resists_type":{},"activates_ability":{},"activates_item":{},"enhances_move":{},"hinders_move":{},"description":"Doubles special defense, and doubles the Pokemon's special attack while taking damage."},{"gen":2,"name":"light_screen","introduced":1,"formatted_name":"Light screen","field_state_class":"screen","damage_percent":0,"max_layers":1,"only_grounded":false,"stat_modifications":{"special_defense":[2,"all_allies",100]},"target":"all_allies","effects":{},"causes_status":{},"prevents_status":{},"boosts_type":{},"resists_type":{},"activates_ability":{},"activates_item":{},"enhances_move":{},"hinders_move":{},"description":"Doubles special defense."},{"gen":3,"name":"light_screen","introduced":1,"formatted_name":"Light screen","field_state_class":"screen","damage_percent":0,"max_layers":1,"only_grounded":false,"stat_modifications":{"special_defense":[1,"all_allies",100]},"target":"all_allies","effects":{},"causes_status":{},"prevents_status":{},"boosts_type":{},"resists_type":{},"activates_ability":{},"activates_item":{},"enhances_move":{},"hinders_move":{},"description":"Cuts the special damage received in half (but does not increase special defense)."},{"gen":4,"name":"light_screen","introduced":1,"formatted_name":"Light screen","field_state_class":"screen","damage_percent":0,"max_layers":1,"only_grounded":false,"stat_modifications":{"special_defense":[1,"all_allies",100]},"target":"all_allies","effects":{},"causes_status":{},"prevents_status":{},"boosts_type":{},"resists_type":{},"activates_ability":{},"activates_item":{},"enhances_move":{},"hinders_move":{},"description":"Cuts the special damage received in half (but does not increase special defense)."},{"gen":5,"name":"light_screen","introduced":1,"formatted_name":"Light screen","field_state_class":"screen","damage_percent":0,"max_layers":1,"only_grounded":false,"stat_modifications":{"special_defense":[1,"all_allies",100]},"target":"all_allies","effects":{},"causes_status":{},"prevents_status":{},"boosts_type":{},"resists_type":{},"activates_ability":{},"activates_item":{},"enhances_move":{},"hinders_move":{},"description":"Cuts the special damage received in half (but does not increase special defense)."},{"gen":6,"name":"light_screen","introduced":1,"formatted_name":"Light screen","field_state_class":"screen","damage_percent":0,"max_layers":1,"only_grounded":false,"stat_modifications":{"special_defense":[1,"all_allies",100]},"target":"all_allies","effects":{},"causes_status":{},"prevents_status":{},"boosts_type":{},"resists_type":{},"activates_ability":{},"activates_item":{},"enhances_move":{},"hinders_move":{},"description":"Cuts the special damage received in half (but does not increase special defense)."},{"gen":7,"name":"light_screen","introduced":1,"formatted_name":"Light screen","field_state_class":"screen","damage_percent":0,"max_layers":1,"only_grounded":false,"stat_modifications":{"special_defense":[1,"all_allies",100]},"target":"all_allies","effects":{},"causes_status":{},"prevents_status":{},"boosts_type":{},"resists_type":{},"activates_ability":{},"activates_item":{},"enhances_move":{},"hinders_move":{},"description":"Cuts the special damage received in half (but does not increase special defense)."},{"gen":8,"name":"light_screen","introduced":1,"formatted_name":"Light screen","field_state_class":"screen","damage_percent":0,"max_layers":1,"only_grounded":false,"stat_modifications":{"special_defense":[1,"all_allies",100]},"target":"all_allies","effects":{},"causes_status":{},"prevents_status":{},"boosts_type":{},"resists_type":{},"activates_ability":{},"activates_item":{},"enhances_move":{},"hinders_move":{},"description":"Cuts the special damage received in half (but does not increase special defense)."},{"gen":7,"name":"aurora_veil","introduced":7,"formatted_name":"Aurora veil","field_state_class":"screen","damage_percent":0,"max_layers":1,"only_grounded":false,"stat_modifications":{},"target":"all_allies","effects":{},"causes_status":{},"prevents_status":{},"boosts_type":{},"resists_type":{},"activates_ability":{},"activates_item":{},"enhances_move":{},"hinders_move":{},"description":"Cuts the physical and special damage received in half (but does not increase defense/special defense)."},{"gen":8,"name":"aurora_veil","introduced":7,"formatted_name":"Aurora veil","field_state_class":"screen","damage_percent":0,"max_layers":1,"only_grounded":false,"stat_modifications":{},"target":"all_allies","effects":{},"causes_status":{},"prevents_status":{},"boosts_type":{},"resists_type":{},"activates_ability":{},"activates_item":{},"enhances_move":{},"hinders_move":{},"description":"Cuts the physical and special damage received in half (but does not increase defense/special defense)."},{"gen":5,"name":"rainbow","introduced":5,"formatted_name":"Rainbow","field_state_class":"pledge","damage_percent":0,"max_layers":1,"only_grounded":false,"stat_modifications":{"secondary_effect_chance":[2,"all_allies",100]},"target":"all_allies","effects":{},"causes_status":{},"prevents_status":{},"boosts_type":{},"resists_type":{},"activates_ability":{},"activates_item":{},"enhances_move":{},"hinders_move":{},"description":"Doubles the chance of secondary effects occuring."},{"gen":6,"name":"rainbow","introduced":5,"formatted_name":"Rainbow","field_state_class":"pledge","damage_percent":0,"max_layers":1,"only_grounded":false,"stat_modifications":{"secondary_effect_chance":[2,"all_allies",100]},"target":"all_allies","effects":{},"causes_status":{},"prevents_status":{},"boosts_type":{},"resists_type":{},"activates_ability":{},"activates_item":{},"enhances_move":{},"hinders_move":{},"description":"Doubles the chance of secondary effects occuring."},{"gen":7,"name":"rainbow","introduced":5,"formatted_name":"Rainbow","field_state_class":"pledge","damage_percent":0,"max_layers":1,"only_grounded":false,"stat_modifications":{"secondary_effect_chance":[2,"all_allies",100]},"target":"all_allies","effects":{},"causes_status":{},"prevents_status":{},"boosts_type":{},"resists_type":{},"activates_ability":{},"activates_item":{},"enhances_move":{},"hinders_move":{},"description":"Doubles the chance of secondary effects occuring."},{"gen":8,"name":"rainbow","introduced":5,"formatted_name":"Rainbow","field_state_class":"pledge","damage_percent":0,"max_layers":1,"only_grounded":false,"stat_modifications":{"secondary_effect_chance":[2,"all_allies",100]},"target":"all_allies","effects":{},"causes_status":{},"prevents_status":{},"boosts_type":{},"resists_type":{},"activates_ability":{},"activates_item":{},"enhances_move":{},"hinders_move":{},"description":"Doubles the chance of secondary effects occuring."},{"gen":5,"name":"sea_of_fire","introduced":5,"formatted_name":"Sea of fire","field_state_class":"pledge","damage_percent":12.5,"max_layers":1,"only_grounded":false,"stat_modifications":{},"target":"all_foes","effects":{},"causes_status":{},"prevents_status":{},"boosts_type":{},"resists_type":{},"activates_ability":{},"activates_item":{},"enhances_move":{},"hinders_move":{},"description":"Damages non-Fire-type Pokemon for 1/8 max HP each turn."},{"gen":6,"name":"sea_of_fire","introduced":5,"formatted_name":"Sea of fire","field_state_class":"pledge","damage_percent":12.5,"max_layers":1,"only_grounded":false,"stat_modifications":{},"target":"all_foes","effects":{},"causes_status":{},"prevents_status":{},"boosts_type":{},"resists_type":{},"activates_ability":{},"activates_item":{},"enhances_move":{},"hinders_move":{},"description":"Damages non-Fire-type Pokemon for 1/8 max HP each turn."},{"gen":7,"name":"sea_of_fire","introduced":5,"formatted_name":"Sea of fire","field_state_class":"pledge","damage_percent":12.5,"max_layers":1,"only_grounded":false,"stat_modifications":{},"target":"all_foes","effects":{},"causes_status":{},"prevents_status":{},"boosts_type":{},"resists_type":{},"activates_ability":{},"activates_item":{},"enhances_move":{},"hinders_move":{},"description":"Damages non-Fire-type Pokemon for 1/8 max HP each turn."},{"gen":8,"name":"sea_of_fire","introduced":5,"formatted_name":"Sea of fire","field_state_class":"pledge","damage_percent":12.5,"max_layers":1,"only_grounded":false,"stat_modifications":{},"target":"all_foes","effects":{},"causes_status":{},"prevents_status":{},"boosts_type":{},"resists_type":{},"activates_ability":{},"activates_item":{},"enhances_move":{},"hinders_move":{},"description":"Damages non-Fire-type Pokemon for 1/8 max HP each turn."},{"gen":5,"name":"swamp","introduced":5,"formatted_name":"Swamp","field_state_class":"pledge","damage_percent":0,"max_layers":1,"only_grounded":false,"stat_modifications":{"speed":[2,"all_foes",100]},"target":"all_foes","effects":{},"causes_status":{},"prevents_status":{},"boosts_type":{},"resists_type":{},"activates_ability":{},"activates_item":{},"enhances_move":{},"hinders_move":{},"description":"Quarters the speed of all affected Pokemon."},{"gen":6,"name":"swamp","introduced":5,"formatted_name":"Swamp","field_state_class":"pledge","damage_percent":0,"max_layers":1,"only_grounded":false,"stat_modifications":{"speed":[2,"all_foes",100]},"target":"all_foes","effects":{},"causes_status":{},"prevents_status":{},"boosts_type":{},"resists_type":{},"activates_ability":{},"activates_item":{},"enhances_move":{},"hinders_move":{},"description":"Quarters the speed of all affected Pokemon."},{"gen":7,"name":"swamp","introduced":5,"formatted_name":"Swamp","field_state_class":"pledge","damage_percent":0,"max_layers":1,"only_grounded":false,"stat_modifications":{"speed":[2,"all_foes",100]},"target":"all_foes","effects":{},"causes_status":{},"prevents_status":{},"boosts_type":{},"resists_type":{},"activates_ability":{},"activates_item":{},"enhances_move":{},"hinders_move":{},"description":"Quarters the speed of all affected Pokemon."},{"gen":8,"name":"swamp","introduced":5,"formatted_name":"Swamp","field_state_class":"pledge","damage_percent":0,"max_layers":1,"only_grounded":false,"stat_modifications":{"speed":[2,"all_foes",100]},"target":"all_foes","effects":{},"causes_status":{},"prevents_status":{},"boosts_type":{},"resists_type":{},"activates_ability":{},"activates_item":{},"enhances_move":{},"hinders_move":{},"description":"Quarters the speed of all affected Pokemon."},{"gen":4,"name":"stealth_rock","introduced":4,"formatted_name":"Stealth rock","field_state_class":"entry_hazard","damage_percent":12.5,"max_layers":1,"only_grounded":false,"stat_modifications":{},"target":"all_foes","effects":{},"causes_status":{},"prevents_status":{},"boosts_type":{},"resists_type":{},"activates_ability":{},"activates_item":{},"enhances_move":{},"hinders_move":{},"description":"Deals Rock-type damage for 1/8 of the Pokemon's max HP on entry."},{"gen":5,"name":"stealth_rock","introduced":4,"formatted_name":"Stealth rock","field_state_class":"entry_hazard","damage_percent":12.5,"max_layers":1,"only_grounded":false,"stat_modifications":{},"target":"all_foes","effects":{},"causes_status":{},"prevents_status":{},"boosts_type":{},"resists_type":{},"activates_ability":{},"activates_item":{},"enhances_move":{},"hinders_move":{},"description":"Deals Rock-type damage for 1/8 of the Pokemon's max HP on entry."},{"gen":6,"name":"stealth_rock","introduced":4,"formatted_name":"Stealth rock","field_state_class":"entry_hazard","damage_percent":12.5,"max_layers":1,"only_grounded":false,"stat_modifications":{},"target":"all_foes","effects":{},"causes_status":{},"prevents_status":{},"boosts_type":{},"resists_type":{},"activates_ability":{},"activates_item":{},"enhances_move":{},"hinders_move":{},"description":"Deals Rock-type damage for 1/8 of the Pokemon's max HP on entry."},{"gen":7,"name":"stealth_rock","introduced":4,"formatted_name":"Stealth rock","field_state_class":"entry_hazard","damage_percent":12.5,"max_layers":1,"only_grounded":false,"stat_modifications":{},"target":"all_foes","effects":{},"causes_status":{},"prevents_status":{},"boosts_type":{},"resists_type":{},"activates_ability":{},"activates_item":{},"enhances_move":{},"hinders_move":{},"description":"Deals Rock-type damage for 1/8 of the Pokemon's max HP on entry."},{"gen":8,"name":"stealth_rock","introduced":4,"formatted_name":"Stealth rock","field_state_class":"entry_hazard","damage_percent":12.5,"max_layers":1,"only_grounded":false,"stat_modifications":{},"target":"all_foes","effects":{},"causes_status":{},"prevents_status":{},"boosts_type":{},"resists_type":{},"activates_ability":{},"activates_item":{},"enhances_move":{},"hinders_move":{},"description":"Deals Rock-type damage for 1/8 of the Pokemon's max HP on entry."},{"gen":2,"name":"spikes","introduced":2,"formatted_name":"Spikes","field_state_class":"entry_hazard","damage_percent":12.5,"max_layers":3,"only_grounded":true,"stat_modifications":{},"target":"all_foes","effects":{},"causes_status":{},"prevents_status":{},"boosts_type":{},"resists_type":{},"activates_ability":{},"activates_item":{},"enhances_move":{},"hinders_move":{},"description":"Deals damage to grounded Pokemon on entry, dependent on their max HP and number of layers present."},{"gen":3,"name":"spikes","introduced":2,"formatted_name":"Spikes","field_state_class":"entry_hazard","damage_percent":12.5,"max_layers":3,"only_grounded":true,"stat_modifications":{},"target":"all_foes","effects":{"only_affects_grounded":true},"causes_status":{},"prevents_status":{},"boosts_type":{},"resists_type":{},"activates_ability":{},"activates_item":{},"enhances_move":{},"hinders_move":{},"description":"Deals damage to grounded Pokemon on entry, dependent on their max HP and number of layers present."},{"gen":4,"name":"spikes","introduced":2,"formatted_name":"Spikes","field_state_class":"entry_hazard","damage_percent":12.5,"max_layers":3,"only_grounded":true,"stat_modifications":{},"target":"all_foes","effects":{"only_affects_grounded":true},"causes_status":{},"prevents_status":{},"boosts_type":{},"resists_type":{},"activates_ability":{},"activates_item":{},"enhances_move":{},"hinders_move":{},"description":"Deals damage to grounded Pokemon on entry, dependent on their max HP and number of layers present."},{"gen":5,"name":"spikes","introduced":2,"formatted_name":"Spikes","field_state_class":"entry_hazard","damage_percent":12.5,"max_layers":3,"only_grounded":true,"stat_modifications":{},"target":"all_foes","effects":{"only_affects_grounded":true},"causes_status":{},"prevents_status":{},"boosts_type":{},"resists_type":{},"activates_ability":{},"activates_item":{},"enhances_move":{},"hinders_move":{},"description":"Deals damage to grounded Pokemon on entry, dependent on their max HP and number of layers present."},{"gen":6,"name":"spikes","introduced":2,"formatted_name":"Spikes","field_state_class":"entry_hazard","damage_percent":12.5,"max_layers":3,"only_grounded":true,"stat_modifications":{},"target":"all_foes","effects":{"only_affects_grounded":true},"causes_status":{},"prevents_status":{},"boosts_type":{},"resists_type":{},"activates_ability":{},"activates_item":{},"enhances_move":{},"hinders_move":{},"description":"Deals damage to grounded Pokemon on entry, dependent on their max HP and number of layers present."},{"gen":7,"name":"spikes","introduced":2,"formatted_name":"Spikes","field_state_class":"entry_hazard","damage_percent":12.5,"max_layers":3,"only_grounded":true,"stat_modifications":{},"target":"all_foes","effects":{"only_affects_grounded":true},"causes_status":{},"prevents_status":{},"boosts_type":{},"resists_type":{},"activates_ability":{},"activates_item":{},"enhances_move":{},"hinders_move":{},"description":"Deals damage to grounded Pokemon on entry, dependent on their max HP and number of layers present."},{"gen":8,"name":"spikes","introduced":2,"formatted_name":"Spikes","field_state_class":"entry_hazard","damage_percent":12.5,"max_layers":3,"only_grounded":true,"stat_modifications":{},"target":"all_foes","effects":{"only_affects_grounded":true},"causes_status":{},"prevents_status":{},"boosts_type":{},"resists_type":{},"activates_ability":{},"activates_item":{},"enhances_move":{},"hinders_move":{},"description":"Deals damage to grounded Pokemon on entry, dependent on their max HP and number of layers present."},{"gen":6,"name":"sticky_web","introduced":6,"formatted_name":"Sticky web","field_state_class":"entry_hazard","damage_percent":0,"max_layers":1,"only_grounded":true,"stat_modifications":{"speed":["-1","all_foes",100]},"target":"all_foes","effects":{"only_affects_grounded":true},"causes_status":{},"prevents_status":{},"boosts_type":{},"resists_type":{},"activates_ability":{},"activates_item":{},"enhances_move":{},"hinders_move":{},"description":"Slows grounded Pokemon on entry."},{"gen":7,"name":"sticky_web","introduced":6,"formatted_name":"Sticky web","field_state_class":"entry_hazard","damage_percent":0,"max_layers":1,"only_grounded":true,"stat_modifications":{"speed":["-1","all_foes",100]},"target":"all_foes","effects":{"only_affects_grounded":true},"causes_status":{},"prevents_status":{},"boosts_type":{},"resists_type":{},"activates_ability":{},"activates_item":{},"enhances_move":{},"hinders_move":{},"description":"Slows grounded Pokemon on entry."},{"gen":8,"name":"sticky_web","introduced":6,"formatted_name":"Sticky web","field_state_class":"entry_hazard","damage_percent":0,"max_layers":1,"only_grounded":true,"stat_modifications":{"speed":["-1","all_foes",100]},"target":"all_foes","effects":{"only_affects_grounded":true},"causes_status":{},"prevents_status":{},"boosts_type":{},"resists_type":{},"activates_ability":{},"activates_item":{},"enhances_move":{},"hinders_move":{},"description":"Slows grounded Pokemon on entry."},{"gen":4,"name":"toxic_spikes","introduced":4,"formatted_name":"Toxic spikes","field_state_class":"entry_hazard","damage_percent":0,"max_layers":2,"only_grounded":true,"stat_modifications":{},"target":"all_foes","effects":{"only_affects_grounded":true},"causes_status":{"poison":100,"bad_poison":100},"prevents_status":{},"boosts_type":{},"resists_type":{},"activates_ability":{},"activates_item":{},"enhances_move":{},"hinders_move":{},"description":"Poisons grounded Pokemon on entry."},{"gen":5,"name":"toxic_spikes","introduced":4,"formatted_name":"Toxic spikes","field_state_class":"entry_hazard","damage_percent":0,"max_layers":2,"only_grounded":true,"stat_modifications":{},"target":"all_foes","effects":{"only_affects_grounded":true},"causes_status":{"poison":100,"bad_poison":100},"prevents_status":{},"boosts_type":{},"resists_type":{},"activates_ability":{},"activates_item":{},"enhances_move":{},"hinders_move":{},"description":"Poisons grounded Pokemon on entry."},{"gen":6,"name":"toxic_spikes","introduced":4,"formatted_name":"Toxic spikes","field_state_class":"entry_hazard","damage_percent":0,"max_layers":2,"only_grounded":true,"stat_modifications":{},"target":"all_foes","effects":{"only_affects_grounded":true},"causes_status":{"poison":100,"bad_poison":100},"prevents_status":{},"boosts_type":{},"resists_type":{},"activates_ability":{},"activates_item":{},"enhances_move":{},"hinders_move":{},"description":"Poisons grounded Pokemon on entry."},{"gen":7,"name":"toxic_spikes","introduced":4,"formatted_name":"Toxic spikes","field_state_class":"entry_hazard","damage_percent":0,"max_layers":2,"only_grounded":true,"stat_modifications":{},"target":"all_foes","effects":{"only_affects_grounded":true},"causes_status":{"poison":100,"bad_poison":100},"prevents_status":{},"boosts_type":{},"resists_type":{},"activates_ability":{},"activates_item":{},"enhances_move":{},"hinders_move":{},"description":"Poisons grounded Pokemon on entry."},{"gen":8,"name":"toxic_spikes","introduced":4,"formatted_name":"Toxic spikes","field_state_class":"entry_hazard","damage_percent":0,"max_layers":2,"only_grounded":true,"stat_modifications":{},"target":"all_foes","effects":{"only_affects_grounded":true},"causes_status":{"poison":100,"bad_poison":100},"prevents_status":{},"boosts_type":{},"resists_type":{},"activates_ability":{},"activates_item":{},"enhances_move":{},"hinders_move":{},"description":"Poisons grounded Pokemon on entry."},{"gen":8,"name":"sharp_steel","introduced":8,"formatted_name":"Sharp steel","field_state_class":"entry_hazard","damage_percent":12.5,"max_layers":1,"only_grounded":false,"stat_modifications":{},"target":"all_foes","effects":{},"causes_status":{},"prevents_status":{},"boosts_type":{},"resists_type":{},"activates_ability":{},"activates_item":{},"enhances_move":{},"hinders_move":{},"description":"Deals Steel-type damage for 1/8 of the Pokemon's max HP on entry."},{"gen":1,"name":"clear_skies","introduced":1,"formatted_name":"Clear skies","field_state_class":"weather","damage_percent":0,"max_layers":1,"only_grounded":false,"stat_modifications":{},"target":"all","effects":{},"causes_status":{},"prevents_status":{},"weather_ball":"normal","boosts_type":{},"resists_type":{},"activates_ability":{},"activates_item":{},"enhances_move":{},"hinders_move":{},"description":"Denotes the absence of other weather effects."},{"gen":2,"name":"clear_skies","introduced":1,"formatted_name":"Clear skies","field_state_class":"weather","damage_percent":0,"max_layers":1,"only_grounded":false,"stat_modifications":{},"target":"all","effects":{},"causes_status":{},"prevents_status":{},"weather_ball":"normal","boosts_type":{},"resists_type":{},"activates_ability":{},"activates_item":{},"enhances_move":{},"hinders_move":{},"description":"Denotes the absence of other weather effects."},{"gen":3,"name":"clear_skies","introduced":1,"formatted_name":"Clear skies","field_state_class":"weather","damage_percent":0,"max_layers":1,"only_grounded":false,"stat_modifications":{},"target":"all","effects":{},"causes_status":{},"prevents_status":{},"weather_ball":"normal","boosts_type":{},"resists_type":{},"activates_ability":{},"activates_item":{},"enhances_move":{},"hinders_move":{},"description":"Denotes the absence of other weather effects."},{"gen":4,"name":"clear_skies","introduced":1,"formatted_name":"Clear skies","field_state_class":"weather","damage_percent":0,"max_layers":1,"only_grounded":false,"stat_modifications":{},"target":"all","effects":{},"causes_status":{},"prevents_status":{},"weather_ball":"normal","boosts_type":{},"resists_type":{},"activates_ability":{},"activates_item":{},"enhances_move":{},"hinders_move":{},"description":"Denotes the absence of other weather effects."},{"gen":5,"name":"clear_skies","introduced":1,"formatted_name":"Clear skies","field_state_class":"weather","damage_percent":0,"max_layers":1,"only_grounded":false,"stat_modifications":{},"target":"all","effects":{},"causes_status":{},"prevents_status":{},"weather_ball":"normal","boosts_type":{},"resists_type":{},"activates_ability":{},"activates_item":{},"enhances_move":{},"hinders_move":{},"description":"Denotes the absence of other weather effects."},{"gen":6,"name":"clear_skies","introduced":1,"formatted_name":"Clear skies","field_state_class":"weather","damage_percent":0,"max_layers":1,"only_grounded":false,"stat_modifications":{},"target":"all","effects":{},"causes_status":{},"prevents_status":{},"weather_ball":"normal","boosts_type":{},"resists_type":{},"activates_ability":{},"activates_item":{},"enhances_move":{},"hinders_move":{},"description":"Denotes the absence of other weather effects."},{"gen":7,"name":"clear_skies","introduced":1,"formatted_name":"Clear skies","field_state_class":"weather","damage_percent":0,"max_layers":1,"only_grounded":false,"stat_modifications":{},"target":"all","effects":{},"causes_status":{},"prevents_status":{},"weather_ball":"normal","boosts_type":{},"resists_type":{},"activates_ability":{},"activates_item":{},"enhances_move":{},"hinders_move":{},"description":"Denotes the absence of other weather effects."},{"gen":8,"name":"clear_skies","introduced":1,"formatted_name":"Clear skies","field_state_class":"weather","damage_percent":0,"max_layers":1,"only_grounded":false,"stat_modifications":{},"target":"all","effects":{},"causes_status":{},"prevents_status":{},"weather_ball":"normal","boosts_type":{},"resists_type":{},"activates_ability":{},"activates_item":{},"enhances_move":{},"hinders_move":{},"description":"Denotes the absence of other weather effects."},{"gen":2,"name":"harsh_sunlight","introduced":2,"formatted_name":"Harsh sunlight","field_state_class":"weather","damage_percent":0,"max_layers":1,"only_grounded":false,"stat_modifications":{},"target":"all","effects":{},"causes_status":{},"prevents_status":{"freeze":true},"weather_ball":"fire","boosts_type":{"fire":1.5},"resists_type":{"water":0.5},"activates_ability":{},"activates_item":{},"enhances_move":{"solar_beam":true,"moonlight":true,"synthesis":true,"morning_sun":true},"hinders_move":{"thunder":true},"description":"Harsh sunlight covers the field, weakening Water-type attacks and strengthing Fire-type attacks."},{"gen":3,"name":"harsh_sunlight","introduced":2,"formatted_name":"Harsh sunlight","field_state_class":"weather","damage_percent":0,"max_layers":1,"only_grounded":false,"stat_modifications":{},"target":"all","effects":{},"causes_status":{},"prevents_status":{"freeze":true},"weather_ball":"fire","boosts_type":{"fire":1.5},"resists_type":{"water":0.5},"activates_ability":{"forecast":true,"chlorophyll":true},"activates_item":{},"enhances_move":{"solar_beam":true,"moonlight":true,"synthesis":true,"morning_sun":true,"weather_ball":true},"hinders_move":{"thunder":true},"description":"Harsh sunlight covers the field, weakening Water-type attacks and strengthing Fire-type attacks."},{"gen":4,"name":"harsh_sunlight","introduced":2,"formatted_name":"Harsh sunlight","field_state_class":"weather","damage_percent":0,"max_layers":1,"only_grounded":false,"stat_modifications":{},"target":"all","effects":{},"causes_status":{},"prevents_status":{"freeze":true},"weather_ball":"fire","boosts_type":{"fire":1.5},"resists_type":{"water":0.5},"activates_ability":{"forecast":true,"dry_skin":true,"chlorophyll":true,"flower_gift":true,"leaf_guard":true,"solar_power":true},"activates_item":{},"enhances_move":{"solar_beam":true,"moonlight":true,"synthesis":true,"morning_sun":true,"weather_ball":true},"hinders_move":{"thunder":true},"description":"Harsh sunlight covers the field, weakening Water-type attacks and strengthing Fire-type attacks."},{"gen":5,"name":"harsh_sunlight","introduced":2,"formatted_name":"Harsh sunlight","field_state_class":"weather","damage_percent":0,"max_layers":1,"only_grounded":false,"stat_modifications":{},"target":"all","effects":{},"causes_status":{},"prevents_status":{"freeze":true},"weather_ball":"fire","boosts_type":{"fire":1.5},"resists_type":{"water":0.5},"activates_ability":{"forecast":true,"dry_skin":true,"chlorophyll":true,"flower_gift":true,"leaf_guard":true,"solar_power":true,"harvest":true},"activates_item":{},"enhances_move":{"solar_beam":true,"growth":true,"moonlight":true,"synthesis":true,"morning_sun":true,"weather_ball":true},"hinders_move":{"thunder":true,"hurricane":true},"description":"Harsh sunlight covers the field, weakening Water-type attacks and strengthing Fire-type attacks."},{"gen":6,"name":"harsh_sunlight","introduced":2,"formatted_name":"Harsh sunlight","field_state_class":"weather","damage_percent":0,"max_layers":1,"only_grounded":false,"stat_modifications":{},"target":"all","effects":{},"causes_status":{},"prevents_status":{"freeze":true},"weather_ball":"fire","boosts_type":{"fire":1.5},"resists_type":{"water":0.5},"activates_ability":{"forecast":true,"dry_skin":true,"chlorophyll":true,"flower_gift":true,"leaf_guard":true,"solar_power":true,"harvest":true},"activates_item":{},"enhances_move":{"solar_beam":true,"growth":true,"moonlight":true,"synthesis":true,"morning_sun":true,"weather_ball":true},"hinders_move":{"thunder":true,"hurricane":true},"description":"Harsh sunlight covers the field, weakening Water-type attacks and strengthing Fire-type attacks."},{"gen":7,"name":"harsh_sunlight","introduced":2,"formatted_name":"Harsh sunlight","field_state_class":"weather","damage_percent":0,"max_layers":1,"only_grounded":false,"stat_modifications":{},"target":"all","effects":{},"causes_status":{},"prevents_status":{"freeze":true},"weather_ball":"fire","boosts_type":{"fire":1.5},"resists_type":{"water":0.5},"activates_ability":{"forecast":true,"dry_skin":true,"chlorophyll":true,"flower_gift":true,"leaf_guard":true,"solar_power":true,"harvest":true},"activates_item":{},"enhances_move":{"solar_beam":true,"solar_blade":true,"growth":true,"moonlight":true,"synthesis":true,"morning_sun":true,"weather_ball":true},"hinders_move":{"thunder":true,"hurricane":true},"description":"Harsh sunlight covers the field, weakening Water-type attacks and strengthing Fire-type attacks."},{"gen":8,"name":"harsh_sunlight","introduced":2,"formatted_name":"Harsh sunlight","field_state_class":"weather","damage_percent":0,"max_layers":1,"only_grounded":false,"stat_modifications":{},"target":"all","effects":{},"causes_status":{},"prevents_status":{"freeze":true},"weather_ball":"fire","boosts_type":{"fire":1.5},"resists_type":{"water":0.5},"activates_ability":{"forecast":true,"dry_skin":true,"chlorophyll":true,"flower_gift":true,"leaf_guard":true,"solar_power":true,"harvest":true},"activates_item":{},"enhances_move":{"solar_beam":true,"solar_blade":true,"growth":true,"moonlight":true,"synthesis":true,"morning_sun":true,"weather_ball":true},"hinders_move":{"thunder":true,"hurricane":true},"description":"Harsh sunlight covers the field, weakening Water-type attacks and strengthing Fire-type attacks."},{"gen":6,"name":"extremely_harsh_sunlight","introduced":6,"formatted_name":"Extremely harsh sunlight","field_state_class":"weather","damage_percent":0,"max_layers":1,"only_grounded":false,"stat_modifications":{},"target":"all","effects":{},"causes_status":{},"prevents_status":{"freeze":true},"weather_ball":"fire","boosts_type":{"fire":1.5},"resists_type":{"water":0},"activates_ability":{"forecast":true,"dry_skin":true,"chlorophyll":true,"flower_gift":true,"leaf_guard":true,"solar_power":true,"harvest":true},"activates_item":{},"enhances_move":{"solar_beam":true,"growth":true,"moonlight":true,"synthesis":true,"morning_sun":true,"weather_ball":true},"hinders_move":{"thunder":true,"hurricane":true},"description":"Extremely harsh sunlight covers the field, nullifying Water-type attacks and strengthing Fire-type attacks."},{"gen":7,"name":"extremely_harsh_sunlight","introduced":6,"formatted_name":"Extremely harsh sunlight","field_state_class":"weather","damage_percent":0,"max_layers":1,"only_grounded":false,"stat_modifications":{},"target":"all","effects":{},"causes_status":{},"prevents_status":{"freeze":true},"weather_ball":"fire","boosts_type":{"fire":1.5},"resists_type":{"water":0},"activates_ability":{"forecast":true,"dry_skin":true,"chlorophyll":true,"flower_gift":true,"leaf_guard":true,"solar_power":true,"harvest":true},"activates_item":{},"enhances_move":{"solar_beam":true,"solar_blade":true,"growth":true,"moonlight":true,"synthesis":true,"morning_sun":true,"weather_ball":true},"hinders_move":{"thunder":true,"hurricane":true},"description":"Extremely harsh sunlight covers the field, nullifying Water-type attacks and strengthing Fire-type attacks."},{"gen":8,"name":"extremely_harsh_sunlight","introduced":6,"formatted_name":"Extremely harsh sunlight","field_state_class":"weather","damage_percent":0,"max_layers":1,"only_grounded":false,"stat_modifications":{},"target":"all","effects":{},"causes_status":{},"prevents_status":{"freeze":true},"weather_ball":"fire","boosts_type":{"fire":1.5},"resists_type":{"water":0},"activates_ability":{"forecast":true,"dry_skin":true,"chlorophyll":true,"flower_gift":true,"leaf_guard":true,"solar_power":true,"harvest":true},"activates_item":{},"enhances_move":{"solar_beam":true,"solar_blade":true,"growth":true,"moonlight":true,"synthesis":true,"morning_sun":true,"weather_ball":true},"hinders_move":{"thunder":true,"hurricane":true},"description":"Extremely harsh sunlight covers the field, nullifying Water-type attacks and strengthing Fire-type attacks."},{"gen":2,"name":"rain","introduced":2,"formatted_name":"Rain","field_state_class":"weather","damage_percent":0,"max_layers":1,"only_grounded":false,"stat_modifications":{},"target":"all","effects":{},"causes_status":{},"prevents_status":{},"weather_ball":"water","boosts_type":{"water":1.5},"resists_type":{"fire":0.5},"activates_ability":{},"activates_item":{},"enhances_move":{"thunder":true},"hinders_move":{"moonlight":true,"synthesis":true,"morning_sun":true},"description":"Rain covers the field, weakening Fire-type attacks and strengthening Water-type attacks."},{"gen":3,"name":"rain","introduced":2,"formatted_name":"Rain","field_state_class":"weather","damage_percent":0,"max_layers":1,"only_grounded":false,"stat_modifications":{},"target":"all","effects":{},"causes_status":{},"prevents_status":{},"weather_ball":"water","boosts_type":{"water":1.5},"resists_type":{"fire":0.5},"activates_ability":{"forecast":true,"rain_dish":true,"swift_swim":true},"activates_item":{},"enhances_move":{"thunder":true,"weather_ball":true},"hinders_move":{"solar_beam":true,"moonlight":true,"synthesis":true,"morning_sun":true},"description":"Rain covers the field, weakening Fire-type attacks and strengthening Water-type attacks."},{"gen":4,"name":"rain","introduced":2,"formatted_name":"Rain","field_state_class":"weather","damage_percent":0,"max_layers":1,"only_grounded":false,"stat_modifications":{},"target":"all","effects":{},"causes_status":{},"prevents_status":{},"weather_ball":"water","boosts_type":{"water":1.5},"resists_type":{"fire":0.5},"activates_ability":{"forecast":true,"dry_skin":true,"hydration":true,"rain_dish":true,"swift_swim":true},"activates_item":{},"enhances_move":{"thunder":true,"weather_ball":true},"hinders_move":{"solar_beam":true,"moonlight":true,"synthesis":true,"morning_sun":true},"description":"Rain covers the field, weakening Fire-type attacks and strengthening Water-type attacks."},{"gen":5,"name":"rain","introduced":2,"formatted_name":"Rain","field_state_class":"weather","damage_percent":0,"max_layers":1,"only_grounded":false,"stat_modifications":{},"target":"all","effects":{},"causes_status":{},"prevents_status":{},"weather_ball":"water","boosts_type":{"water":1.5},"resists_type":{"fire":0.5},"activates_ability":{"forecast":true,"dry_skin":true,"hydration":true,"rain_dish":true,"swift_swim":true},"activates_item":{},"enhances_move":{"thunder":true,"hurricane":true,"weather_ball":true},"hinders_move":{"solar_beam":true,"moonlight":true,"synthesis":true,"morning_sun":true},"description":"Rain covers the field, weakening Fire-type attacks and strengthening Water-type attacks."},{"gen":6,"name":"rain","introduced":2,"formatted_name":"Rain","field_state_class":"weather","damage_percent":0,"max_layers":1,"only_grounded":false,"stat_modifications":{},"target":"all","effects":{},"causes_status":{},"prevents_status":{},"weather_ball":"water","boosts_type":{"water":1.5},"resists_type":{"fire":0.5},"activates_ability":{"forecast":true,"dry_skin":true,"hydration":true,"rain_dish":true,"swift_swim":true},"activates_item":{},"enhances_move":{"thunder":true,"hurricane":true,"weather_ball":true},"hinders_move":{"solar_beam":true,"moonlight":true,"synthesis":true,"morning_sun":true},"description":"Rain covers the field, weakening Fire-type attacks and strengthening Water-type attacks."},{"gen":7,"name":"rain","introduced":2,"formatted_name":"Rain","field_state_class":"weather","damage_percent":0,"max_layers":1,"only_grounded":false,"stat_modifications":{},"target":"all","effects":{},"causes_status":{},"prevents_status":{},"weather_ball":"water","boosts_type":{"water":1.5},"resists_type":{"fire":0.5},"activates_ability":{"forecast":true,"dry_skin":true,"hydration":true,"rain_dish":true,"swift_swim":true},"activates_item":{},"enhances_move":{"thunder":true,"hurricane":true,"weather_ball":true},"hinders_move":{"solar_beam":true,"solar_blade":true,"moonlight":true,"synthesis":true,"morning_sun":true},"description":"Rain covers the field, weakening Fire-type attacks and strengthening Water-type attacks."},{"gen":8,"name":"rain","introduced":2,"formatted_name":"Rain","field_state_class":"weather","damage_percent":0,"max_layers":1,"only_grounded":false,"stat_modifications":{},"target":"all","effects":{},"causes_status":{},"prevents_status":{},"weather_ball":"water","boosts_type":{"water":1.5},"resists_type":{"fire":0.5},"activates_ability":{"forecast":true,"dry_skin":true,"hydration":true,"rain_dish":true,"swift_swim":true},"activates_item":{},"enhances_move":{"thunder":true,"hurricane":true,"weather_ball":true},"hinders_move":{"solar_beam":true,"solar_blade":true,"moonlight":true,"synthesis":true,"morning_sun":true},"description":"Rain covers the field, weakening Fire-type attacks and strengthening Water-type attacks."},{"gen":6,"name":"heavy_rain","introduced":6,"formatted_name":"Heavy rain","field_state_class":"weather","damage_percent":0,"max_layers":1,"only_grounded":false,"stat_modifications":{},"target":"all","effects":{},"causes_status":{},"prevents_status":{},"weather_ball":"water","boosts_type":{"water":1.5},"resists_type":{"fire":0},"activates_ability":{"forecast":true,"dry_skin":true,"hydration":true,"rain_dish":true,"swift_swim":true},"activates_item":{},"enhances_move":{"thunder":true,"hurricane":true,"weather_ball":true},"hinders_move":{"solar_beam":true,"moonlight":true,"synthesis":true,"morning_sun":true},"description":"A torrent of rain drenches the field, nullifying Fire-type attacks and strengthening Water-type attacks."},{"gen":7,"name":"heavy_rain","introduced":6,"formatted_name":"Heavy rain","field_state_class":"weather","damage_percent":0,"max_layers":1,"only_grounded":false,"stat_modifications":{},"target":"all","effects":{},"causes_status":{},"prevents_status":{},"weather_ball":"water","boosts_type":{"water":1.5},"resists_type":{"fire":0},"activates_ability":{"forecast":true,"dry_skin":true,"hydration":true,"rain_dish":true,"swift_swim":true},"activates_item":{},"enhances_move":{"thunder":true,"hurricane":true,"weather_ball":true},"hinders_move":{"solar_beam":true,"solar_blade":true,"moonlight":true,"synthesis":true,"morning_sun":true},"description":"A torrent of rain drenches the field, nullifying Fire-type attacks and strengthening Water-type attacks."},{"gen":8,"name":"heavy_rain","introduced":6,"formatted_name":"Heavy rain","field_state_class":"weather","damage_percent":0,"max_layers":1,"only_grounded":false,"stat_modifications":{},"target":"all","effects":{},"causes_status":{},"prevents_status":{},"weather_ball":"water","boosts_type":{"water":1.5},"resists_type":{"fire":0},"activates_ability":{"forecast":true,"dry_skin":true,"hydration":true,"rain_dish":true,"swift_swim":true},"activates_item":{},"enhances_move":{"thunder":true,"hurricane":true,"weather_ball":true},"hinders_move":{"solar_beam":true,"solar_blade":true,"moonlight":true,"synthesis":true,"morning_sun":true},"description":"A torrent of rain drenches the field, nullifying Fire-type attacks and strengthening Water-type attacks."},{"gen":2,"name":"sandstorm","introduced":2,"formatted_name":"Sandstorm","field_state_class":"weather","damage_percent":6.25,"max_layers":1,"only_grounded":false,"stat_modifications":{},"target":"all","effects":{},"causes_status":{},"prevents_status":{},"weather_ball":"rock","boosts_type":{},"resists_type":{},"activates_ability":{},"activates_item":{},"enhances_move":{},"hinders_move":{},"description":"A tempest of sand batters the field, causing damage over time."},{"gen":3,"name":"sandstorm","introduced":2,"formatted_name":"Sandstorm","field_state_class":"weather","damage_percent":6.25,"max_layers":1,"only_grounded":false,"stat_modifications":{},"target":"all","effects":{},"causes_status":{},"prevents_status":{},"weather_ball":"rock","boosts_type":{},"resists_type":{},"activates_ability":{"forecast":true,"sand_veil":true},"activates_item":{},"enhances_move":{"weather_ball":true},"hinders_move":{"solar_beam":true},"description":"A tempest of sand batters the field, causing damage over time."},{"gen":4,"name":"sandstorm","introduced":2,"formatted_name":"Sandstorm","field_state_class":"weather","damage_percent":6.25,"max_layers":1,"only_grounded":false,"stat_modifications":{"special_defense":[1.5,"all_allies",100]},"target":"all","effects":{},"causes_status":{},"prevents_status":{},"weather_ball":"rock","boosts_type":{},"resists_type":{},"activates_ability":{"forecast":true,"sand_veil":true},"activates_item":{},"enhances_move":{"weather_ball":true},"hinders_move":{"solar_beam":true},"description":"A tempest of sand batters the field, causing damage over time."},{"gen":5,"name":"sandstorm","introduced":2,"formatted_name":"Sandstorm","field_state_class":"weather","damage_percent":6.25,"max_layers":1,"only_grounded":false,"stat_modifications":{"special_defense":[1.5,"all_allies",100]},"target":"all","effects":{},"causes_status":{},"prevents_status":{},"weather_ball":"rock","boosts_type":{},"resists_type":{},"activates_ability":{"forecast":true,"sand_veil":true,"sand_rush":true,"sand_force":true},"activates_item":{},"enhances_move":{"weather_ball":true},"hinders_move":{"solar_beam":true},"description":"A tempest of sand batters the field, causing damage over time."},{"gen":6,"name":"sandstorm","introduced":2,"formatted_name":"Sandstorm","field_state_class":"weather","damage_percent":6.25,"max_layers":1,"only_grounded":false,"stat_modifications":{"special_defense":[1.5,"all_allies",100]},"target":"all","effects":{},"causes_status":{},"prevents_status":{},"weather_ball":"rock","boosts_type":{},"resists_type":{},"activates_ability":{"forecast":true,"sand_veil":true,"sand_rush":true,"sand_force":true},"activates_item":{},"enhances_move":{"weather_ball":true},"hinders_move":{"solar_beam":true},"description":"A tempest of sand batters the field, causing damage over time."},{"gen":7,"name":"sandstorm","introduced":2,"formatted_name":"Sandstorm","field_state_class":"weather","damage_percent":6.25,"max_layers":1,"only_grounded":false,"stat_modifications":{"special_defense":[1.5,"all_allies",100]},"target":"all","effects":{},"causes_status":{},"prevents_status":{},"weather_ball":"rock","boosts_type":{},"resists_type":{},"activates_ability":{"forecast":true,"sand_veil":true,"sand_rush":true,"sand_force":true},"activates_item":{},"enhances_move":{"shore_up":true,"weather_ball":true},"hinders_move":{"solar_beam":true,"solar_blade":true,"shore_up":true},"description":"A tempest of sand batters the field, causing damage over time."},{"gen":8,"name":"sandstorm","introduced":2,"formatted_name":"Sandstorm","field_state_class":"weather","damage_percent":6.25,"max_layers":1,"only_grounded":false,"stat_modifications":{"special_defense":[1.5,"all_allies",100]},"target":"all","effects":{},"causes_status":{},"prevents_status":{},"weather_ball":"rock","boosts_type":{},"resists_type":{},"activates_ability":{"forecast":true,"sand_veil":true,"sand_rush":true,"sand_force":true},"activates_item":{},"enhances_move":{"shore_up":true,"weather_ball":true},"hinders_move":{"solar_beam":true,"solar_blade":true,"shore_up":true},"description":"A tempest of sand batters the field, causing damage over time."},{"gen":3,"name":"hail","introduced":3,"formatted_name":"Hail","field_state_class":"weather","damage_percent":6.25,"max_layers":1,"only_grounded":false,"stat_modifications":{},"target":"all","effects":{},"causes_status":{},"prevents_status":{},"weather_ball":"ice","boosts_type":{},"resists_type":{},"activates_ability":{},"activates_item":{},"enhances_move":{"weather_ball":true},"hinders_move":{"moonlight":true,"synthesis":true,"morning_sun":true},"description":"A tempest of ice batters the field, causing damage over time."},{"gen":4,"name":"hail","introduced":3,"formatted_name":"Hail","field_state_class":"weather","damage_percent":6.25,"max_layers":1,"only_grounded":false,"stat_modifications":{},"target":"all","effects":{},"causes_status":{},"prevents_status":{},"weather_ball":"ice","boosts_type":{},"resists_type":{},"activates_ability":{"ice_body":true,"snow_cloak":true},"activates_item":{},"enhances_move":{"blizzard":true,"weather_ball":true},"hinders_move":{"moonlight":true,"synthesis":true,"morning_sun":true},"description":"A tempest of ice batters the field, causing damage over time."},{"gen":5,"name":"hail","introduced":3,"formatted_name":"Hail","field_state_class":"weather","damage_percent":6.25,"max_layers":1,"only_grounded":false,"stat_modifications":{},"target":"all","effects":{},"causes_status":{},"prevents_status":{},"weather_ball":"ice","boosts_type":{},"resists_type":{},"activates_ability":{"ice_body":true,"snow_cloak":true},"activates_item":{},"enhances_move":{"blizzard":true,"weather_ball":true},"hinders_move":{"moonlight":true,"synthesis":true,"morning_sun":true},"description":"A tempest of ice batters the field, causing damage over time."},{"gen":6,"name":"hail","introduced":3,"formatted_name":"Hail","field_state_class":"weather","damage_percent":6.25,"max_layers":1,"only_grounded":false,"stat_modifications":{},"target":"all","effects":{},"causes_status":{},"prevents_status":{},"weather_ball":"ice","boosts_type":{},"resists_type":{},"activates_ability":{"ice_body":true,"snow_cloak":true},"activates_item":{},"enhances_move":{"blizzard":true,"weather_ball":true},"hinders_move":{"moonlight":true,"synthesis":true,"morning_sun":true},"description":"A tempest of ice batters the field, causing damage over time."},{"gen":7,"name":"hail","introduced":3,"formatted_name":"Hail","field_state_class":"weather","damage_percent":6.25,"max_layers":1,"only_grounded":false,"stat_modifications":{},"target":"all","effects":{},"causes_status":{},"prevents_status":{},"weather_ball":"ice","boosts_type":{},"resists_type":{},"activates_ability":{"ice_body":true,"snow_cloak":true,"slush_rush":true},"activates_item":{},"enhances_move":{"blizzard":true,"weather_ball":true},"hinders_move":{"moonlight":true,"synthesis":true,"morning_sun":true},"description":"A tempest of ice batters the field, causing damage over time."},{"gen":8,"name":"hail","introduced":3,"formatted_name":"Hail","field_state_class":"weather","damage_percent":6.25,"max_layers":1,"only_grounded":false,"stat_modifications":{},"target":"all","effects":{},"causes_status":{},"prevents_status":{},"weather_ball":"ice","boosts_type":{},"resists_type":{},"activates_ability":{"ice_body":true,"snow_cloak":true,"slush_rush":true,"ice_face":true},"activates_item":{},"enhances_move":{"blizzard":true,"weather_ball":true},"hinders_move":{"moonlight":true,"synthesis":true,"morning_sun":true},"description":"A tempest of ice batters the field, causing damage over time."},{"gen":4,"name":"fog","introduced":4,"formatted_name":"Fog","field_state_class":"weather","damage_percent":0,"max_layers":1,"only_grounded":false,"stat_modifications":{"accuracy":[0.6,"all",100]},"target":"all","effects":{},"causes_status":{},"prevents_status":{},"weather_ball":"normal","boosts_type":{},"resists_type":{},"activates_ability":{},"activates_item":{},"enhances_move":{},"hinders_move":{"solar_beam":true,"moonlight":true,"synthesis":true,"morning_sun":true},"description":"A dense layer of fog blankets the field, reducing accuracy."},{"gen":5,"name":"fog","introduced":4,"formatted_name":"Fog","field_state_class":"weather","damage_percent":0,"max_layers":1,"only_grounded":false,"stat_modifications":{"accuracy":[0.6,"all",100]},"target":"all","effects":{},"causes_status":{},"prevents_status":{},"weather_ball":"normal","boosts_type":{},"resists_type":{},"activates_ability":{},"activates_item":{},"enhances_move":{},"hinders_move":{"solar_beam":true,"moonlight":true,"synthesis":true,"morning_sun":true},"description":"A dense layer of fog blankets the field, reducing accuracy."},{"gen":6,"name":"fog","introduced":4,"formatted_name":"Fog","field_state_class":"weather","damage_percent":0,"max_layers":1,"only_grounded":false,"stat_modifications":{"accuracy":[0.6,"all",100]},"target":"all","effects":{},"causes_status":{},"prevents_status":{},"weather_ball":"normal","boosts_type":{},"resists_type":{},"activates_ability":{},"activates_item":{},"enhances_move":{},"hinders_move":{"solar_beam":true,"moonlight":true,"synthesis":true,"morning_sun":true},"description":"A dense layer of fog blankets the field, reducing accuracy."},{"gen":7,"name":"fog","introduced":4,"formatted_name":"Fog","field_state_class":"weather","damage_percent":0,"max_layers":1,"only_grounded":false,"stat_modifications":{"accuracy":[0.6,"all",100]},"target":"all","effects":{},"causes_status":{},"prevents_status":{},"weather_ball":"normal","boosts_type":{},"resists_type":{},"activates_ability":{},"activates_item":{},"enhances_move":{},"hinders_move":{"solar_beam":true,"moonlight":true,"synthesis":true,"morning_sun":true},"description":"A dense layer of fog blankets the field, reducing accuracy."},{"gen":8,"name":"fog","introduced":4,"formatted_name":"Fog","field_state_class":"weather","damage_percent":0,"max_layers":1,"only_grounded":false,"stat_modifications":{"accuracy":[0.6,"all",100]},"target":"all","effects":{},"causes_status":{},"prevents_status":{},"weather_ball":"normal","boosts_type":{},"resists_type":{},"activates_ability":{},"activates_item":{},"enhances_move":{},"hinders_move":{"solar_beam":true,"moonlight":true,"synthesis":true,"morning_sun":true},"description":"A dense layer of fog blankets the field, reducing accuracy."},{"gen":6,"name":"strong_winds","introduced":6,"formatted_name":"Strong winds","field_state_class":"weather","damage_percent":0,"max_layers":1,"only_grounded":false,"stat_modifications":{},"target":"all","effects":{"other_move_resistance":true},"causes_status":{},"prevents_status":{},"weather_ball":"normal","boosts_type":{},"resists_type":{},"activates_ability":{},"activates_item":{},"enhances_move":{},"hinders_move":{},"description":"Strong winds blow on the field, preventing most other weather effects, and making moves that would be super effective against pure Flying-type Pokemon to be only normally effective against those Pokemon."},{"gen":7,"name":"strong_winds","introduced":6,"formatted_name":"Strong winds","field_state_class":"weather","damage_percent":0,"max_layers":1,"only_grounded":false,"stat_modifications":{},"target":"all","effects":{"other_move_resistance":true},"causes_status":{},"prevents_status":{},"weather_ball":"normal","boosts_type":{},"resists_type":{},"activates_ability":{},"activates_item":{},"enhances_move":{},"hinders_move":{},"description":"Strong winds blow on the field, preventing most other weather effects, and making moves that would be super effective against pure Flying-type Pokemon to be only normally effective against those Pokemon."},{"gen":8,"name":"strong_winds","introduced":6,"formatted_name":"Strong winds","field_state_class":"weather","damage_percent":0,"max_layers":1,"only_grounded":false,"stat_modifications":{},"target":"all","effects":{"other_move_resistance":true},"causes_status":{},"prevents_status":{},"weather_ball":"normal","boosts_type":{},"resists_type":{},"activates_ability":{},"activates_item":{},"enhances_move":{},"hinders_move":{},"description":"Strong winds blow on the field, preventing most other weather effects, and making moves that would be super effective against pure Flying-type Pokemon to be only normally effective against those Pokemon."},{"gen":6,"name":"electric_terrain","introduced":6,"formatted_name":"Electric terrain","field_state_class":"terrain","damage_percent":0,"max_layers":1,"only_grounded":true,"stat_modifications":{},"target":"all","effects":{"only_affects_grounded":true},"causes_status":{},"prevents_status":{"sleep":true,"drowsy":true},"boosts_type":{"electric":1.5},"resists_type":{},"activates_ability":{},"activates_item":{},"enhances_move":{},"hinders_move":{},"description":"Electricity covers the field, boosting the power of Electric-type moves."},{"gen":7,"name":"electric_terrain","introduced":6,"formatted_name":"Electric terrain","field_state_class":"terrain","damage_percent":0,"max_layers":1,"only_grounded":true,"stat_modifications":{},"target":"all","effects":{"only_affects_grounded":true},"causes_status":{},"prevents_status":{"sleep":true,"drowsy":true},"boosts_type":{"electric":1.5},"resists_type":{},"activates_ability":{"surge_surfer":true},"activates_item":{"electric_seed":true},"enhances_move":{},"hinders_move":{},"description":"Electricity covers the field, boosting the power of Electric-type moves."},{"gen":8,"name":"electric_terrain","introduced":6,"formatted_name":"Electric terrain","field_state_class":"terrain","damage_percent":0,"max_layers":1,"only_grounded":true,"stat_modifications":{},"target":"all","effects":{"only_affects_grounded":true},"causes_status":{},"prevents_status":{"sleep":true,"drowsy":true},"boosts_type":{"electric":1.3},"resists_type":{},"activates_ability":{"surge_surfer":true,"mimicry":true},"activates_item":{"electric_seed":true},"enhances_move":{"rising_voltage":true,"terrain_pulse":true},"hinders_move":{},"description":"Electricity covers the field, boosting the power of Electric-type moves."},{"gen":6,"name":"grassy_terrain","introduced":6,"formatted_name":"Grassy terrain","field_state_class":"terrain","damage_percent":0,"max_layers":1,"only_grounded":true,"stat_modifications":{},"target":"all","effects":{"only_affects_grounded":true,"restores_hp":true},"causes_status":{},"prevents_status":{},"boosts_type":{"grass":1.5},"resists_type":{},"activates_ability":{"grass_pelt":true},"activates_item":{},"enhances_move":{},"hinders_move":{"bulldoze":true,"earthquake":true,"magnitude":true},"description":"Grass covers the field, boosting the power of Grass-type moves."},{"gen":7,"name":"grassy_terrain","introduced":6,"formatted_name":"Grassy terrain","field_state_class":"terrain","damage_percent":0,"max_layers":1,"only_grounded":true,"stat_modifications":{},"target":"all","effects":{"only_affects_grounded":true,"restores_hp":true},"causes_status":{},"prevents_status":{},"boosts_type":{"grass":1.5},"resists_type":{},"activates_ability":{"grass_pelt":true},"activates_item":{"grassy_seed":true},"enhances_move":{"floral_healing":true},"hinders_move":{"bulldoze":true,"earthquake":true,"magnitude":true},"description":"Grass covers the field, boosting the power of Grass-type moves."},{"gen":8,"name":"grassy_terrain","introduced":6,"formatted_name":"Grassy terrain","field_state_class":"terrain","damage_percent":0,"max_layers":1,"only_grounded":true,"stat_modifications":{},"target":"all","effects":{"only_affects_grounded":true,"restores_hp":true},"causes_status":{},"prevents_status":{},"boosts_type":{"grass":1.3},"resists_type":{},"activates_ability":{"grass_pelt":true,"mimicry":true},"activates_item":{"grassy_seed":true},"enhances_move":{"terrain_pulse":true,"grassy_glide":true,"floral_healing":true},"hinders_move":{"bulldoze":true,"earthquake":true,"magnitude":true},"description":"Grass covers the field, boosting the power of Grass-type moves."},{"gen":6,"name":"misty_terrain","introduced":6,"formatted_name":"Misty terrain","field_state_class":"terrain","damage_percent":0,"max_layers":1,"only_grounded":true,"stat_modifications":{},"target":"all","effects":{"only_affects_grounded":true},"causes_status":{},"prevents_status":{"burn":true,"freeze":true,"paralysis":true,"poison":true,"bad_poison":true,"sleep":true,"confusion":true,"drowsy":true},"boosts_type":{},"resists_type":{"dragon":0.5},"activates_ability":{},"activates_item":{},"enhances_move":{},"hinders_move":{},"description":"Mist covers the field, weakening the power of Dragon-type moves."},{"gen":7,"name":"misty_terrain","introduced":6,"formatted_name":"Misty terrain","field_state_class":"terrain","damage_percent":0,"max_layers":1,"only_grounded":true,"stat_modifications":{},"target":"all","effects":{"only_affects_grounded":true},"causes_status":{},"prevents_status":{"burn":true,"freeze":true,"paralysis":true,"poison":true,"bad_poison":true,"sleep":true,"confusion":true,"drowsy":true},"boosts_type":{},"resists_type":{"dragon":0.5},"activates_ability":{},"activates_item":{"misty_seed":true},"enhances_move":{},"hinders_move":{},"description":"Mist covers the field, weakening the power of Dragon-type moves."},{"gen":8,"name":"misty_terrain","introduced":6,"formatted_name":"Misty terrain","field_state_class":"terrain","damage_percent":0,"max_layers":1,"only_grounded":true,"stat_modifications":{},"target":"all","effects":{"only_affects_grounded":true},"causes_status":{},"prevents_status":{"burn":true,"freeze":true,"paralysis":true,"poison":true,"bad_poison":true,"sleep":true,"confusion":true,"drowsy":true},"boosts_type":{},"resists_type":{"dragon":0.5},"activates_ability":{"mimicry":true},"activates_item":{"misty_seed":true},"enhances_move":{"misty_explosion":true,"terrain_pulse":true},"hinders_move":{},"description":"Mist covers the field, weakening the power of Dragon-type moves."},{"gen":6,"name":"psychic_terrain","introduced":6,"formatted_name":"Psychic terrain","field_state_class":"terrain","damage_percent":0,"max_layers":1,"only_grounded":true,"stat_modifications":{},"target":"all","effects":{"only_affects_grounded":true,"protects_against_priority":true},"causes_status":{},"prevents_status":{},"boosts_type":{"psychic":1.5},"resists_type":{},"activates_ability":{},"activates_item":{},"enhances_move":{},"hinders_move":{},"description":"Psychic energies cover the field, boosting the power of Psychic-type moves."},{"gen":7,"name":"psychic_terrain","introduced":6,"formatted_name":"Psychic terrain","field_state_class":"terrain","damage_percent":0,"max_layers":1,"only_grounded":true,"stat_modifications":{},"target":"all","effects":{"only_affects_grounded":true,"protects_against_priority":true},"causes_status":{},"prevents_status":{},"boosts_type":{"psychic":1.5},"resists_type":{},"activates_ability":{},"activates_item":{"psychic_seed":true},"enhances_move":{},"hinders_move":{},"description":"Psychic energies cover the field, boosting the power of Psychic-type moves."},{"gen":8,"name":"psychic_terrain","introduced":6,"formatted_name":"Psychic terrain","field_state_class":"terrain","damage_percent":0,"max_layers":1,"only_grounded":true,"stat_modifications":{},"target":"all","effects":{"only_affects_grounded":true,"protects_against_priority":true},"causes_status":{},"prevents_status":{},"boosts_type":{"psychic":1.3},"resists_type":{},"activates_ability":{"mimicry":true},"activates_item":{"psychic_seed":true},"enhances_move":{"expanding_force":true,"terrain_pulse":true},"hinders_move":{},"description":"Psychic energies cover the field, boosting the power of Psychic-type moves."},{"gen":4,"name":"trick_room","introduced":4,"formatted_name":"Trick room","field_state_class":"room","damage_percent":0,"max_layers":1,"only_grounded":false,"stat_modifications":{},"target":"all","effects":{"other_move_order_change":true},"causes_status":{},"prevents_status":{},"boosts_type":{},"resists_type":{},"activates_ability":{},"activates_item":{},"enhances_move":{},"hinders_move":{},"description":"A tricky room which reverses the move order within each priority bracket."},{"gen":5,"name":"trick_room","introduced":4,"formatted_name":"Trick room","field_state_class":"room","damage_percent":0,"max_layers":1,"only_grounded":false,"stat_modifications":{},"target":"all","effects":{"other_move_order_change":true},"causes_status":{},"prevents_status":{},"boosts_type":{},"resists_type":{},"activates_ability":{},"activates_item":{},"enhances_move":{},"hinders_move":{},"description":"A tricky room which reverses the move order within each priority bracket."},{"gen":6,"name":"trick_room","introduced":4,"formatted_name":"Trick room","field_state_class":"room","damage_percent":0,"max_layers":1,"only_grounded":false,"stat_modifications":{},"target":"all","effects":{"other_move_order_change":true},"causes_status":{},"prevents_status":{},"boosts_type":{},"resists_type":{},"activates_ability":{},"activates_item":{},"enhances_move":{},"hinders_move":{},"description":"A tricky room which reverses the move order within each priority bracket."},{"gen":7,"name":"trick_room","introduced":4,"formatted_name":"Trick room","field_state_class":"room","damage_percent":0,"max_layers":1,"only_grounded":false,"stat_modifications":{},"target":"all","effects":{"other_move_order_change":true},"causes_status":{},"prevents_status":{},"boosts_type":{},"resists_type":{},"activates_ability":{},"activates_item":{},"enhances_move":{},"hinders_move":{},"description":"A tricky room which reverses the move order within each priority bracket."},{"gen":8,"name":"trick_room","introduced":4,"formatted_name":"Trick room","field_state_class":"room","damage_percent":0,"max_layers":1,"only_grounded":false,"stat_modifications":{},"target":"all","effects":{"other_move_order_change":true},"causes_status":{},"prevents_status":{},"boosts_type":{},"resists_type":{},"activates_ability":{},"activates_item":{"room_service":true},"enhances_move":{},"hinders_move":{},"description":"A tricky room which reverses the move order within each priority bracket."},{"gen":5,"name":"magic_room","introduced":5,"formatted_name":"Magic room","field_state_class":"room","damage_percent":0,"max_layers":1,"only_grounded":false,"stat_modifications":{},"target":"all","effects":{"manipulates_item":true},"causes_status":{},"prevents_status":{},"boosts_type":{},"resists_type":{},"activates_ability":{},"activates_item":{},"enhances_move":{},"hinders_move":{},"description":"A magical room in which Pokemon cannot use their held items."},{"gen":6,"name":"magic_room","introduced":5,"formatted_name":"Magic room","field_state_class":"room","damage_percent":0,"max_layers":1,"only_grounded":false,"stat_modifications":{},"target":"all","effects":{"manipulates_item":true},"causes_status":{},"prevents_status":{},"boosts_type":{},"resists_type":{},"activates_ability":{},"activates_item":{},"enhances_move":{},"hinders_move":{},"description":"A magical room in which Pokemon cannot use their held items."},{"gen":7,"name":"magic_room","introduced":5,"formatted_name":"Magic room","field_state_class":"room","damage_percent":0,"max_layers":1,"only_grounded":false,"stat_modifications":{},"target":"all","effects":{"manipulates_item":true},"causes_status":{},"prevents_status":{},"boosts_type":{},"resists_type":{},"activates_ability":{},"activates_item":{},"enhances_move":{},"hinders_move":{},"description":"A magical room in which Pokemon cannot use their held items."},{"gen":8,"name":"magic_room","introduced":5,"formatted_name":"Magic room","field_state_class":"room","damage_percent":0,"max_layers":1,"only_grounded":false,"stat_modifications":{},"target":"all","effects":{"manipulates_item":true},"causes_status":{},"prevents_status":{},"boosts_type":{},"resists_type":{},"activates_ability":{},"activates_item":{},"enhances_move":{},"hinders_move":{},"description":"A magical room in which Pokemon cannot use their held items."},{"gen":5,"name":"wonder_room","introduced":5,"formatted_name":"Wonder room","field_state_class":"room","damage_percent":0,"max_layers":1,"only_grounded":false,"stat_modifications":{},"target":"all","effects":{},"causes_status":{},"prevents_status":{},"boosts_type":{},"resists_type":{},"activates_ability":{},"activates_item":{},"enhances_move":{},"hinders_move":{},"description":"A wondrous room which swaps the Defense and Special Defense of all Pokemon."},{"gen":6,"name":"wonder_room","introduced":5,"formatted_name":"Wonder room","field_state_class":"room","damage_percent":0,"max_layers":1,"only_grounded":false,"stat_modifications":{},"target":"all","effects":{},"causes_status":{},"prevents_status":{},"boosts_type":{},"resists_type":{},"activates_ability":{},"activates_item":{},"enhances_move":{},"hinders_move":{},"description":"A wondrous room which swaps the Defense and Special Defense of all Pokemon."},{"gen":7,"name":"wonder_room","introduced":5,"formatted_name":"Wonder room","field_state_class":"room","damage_percent":0,"max_layers":1,"only_grounded":false,"stat_modifications":{},"target":"all","effects":{},"causes_status":{},"prevents_status":{},"boosts_type":{},"resists_type":{},"activates_ability":{},"activates_item":{},"enhances_move":{},"hinders_move":{},"description":"A wondrous room which swaps the Defense and Special Defense of all Pokemon."},{"gen":8,"name":"wonder_room","introduced":5,"formatted_name":"Wonder room","field_state_class":"room","damage_percent":0,"max_layers":1,"only_grounded":false,"stat_modifications":{},"target":"all","effects":{},"causes_status":{},"prevents_status":{},"boosts_type":{},"resists_type":{},"activates_ability":{},"activates_item":{},"enhances_move":{},"hinders_move":{},"description":"A wondrous room which swaps the Defense and Special Defense of all Pokemon."}]